tf_coder_colab_logging/__init__.py
tf_coder_colab_logging/colab_logging.py
tf_coder_colab_logging/colab_logging_test.py
tf_coder_colab_logging/serialization.py
tf_coder_colab_logging/serialization_test.py
tf_coder_colab_logging/version.py
tensorflow_coder_colab_logging-0.0.4.dist-info/LICENSE
tensorflow_coder_colab_logging-0.0.4.dist-info/METADATA
tensorflow_coder_colab_logging-0.0.4.dist-info/WHEEL
tensorflow_coder_colab_logging-0.0.4.dist-info/top_level.txt
tensorflow_coder_colab_logging-0.0.4.dist-info/RECORD
