Metadata-Version: 2.1
Name: tensorflow-coder-colab-logging
Version: 0.0.4
Summary: Logging utilities for TensorFlow Coder's Colab interface
Home-page: https://github.com/google-research/tensorflow-coder
Author: Google LLC
Author-email: no-reply@google.com
License: UNKNOWN
Keywords: tensorflow coder tf-coder
Platform: UNKNOWN
Classifier: License :: OSI Approved :: Apache Software License
Classifier: Operating System :: OS Independent
Classifier: Programming Language :: Python :: 3
Classifier: Programming Language :: Python :: 3.6
Classifier: Programming Language :: Python :: 3.7
Classifier: Programming Language :: Python :: 3.8
Requires-Python: >=3
Requires-Dist: absl-py (>=0.6.1)
Requires-Dist: numpy (>=1.15.4)
Requires-Dist: mock (>=3.0.5)
Requires-Dist: tensorflow (>=2.2.0)
